plugins/__init__.py
plugins/plugins.py
plugins4all_IcemasterEric-0.0.1.dist-info/LICENSE
plugins4all_IcemasterEric-0.0.1.dist-info/METADATA
plugins4all_IcemasterEric-0.0.1.dist-info/WHEEL
plugins4all_IcemasterEric-0.0.1.dist-info/top_level.txt
plugins4all_IcemasterEric-0.0.1.dist-info/RECORD
